Metadata-Version: 2.1
Name: ndjsonTosvg
Version: 0.0.1
Summary: ndjsonTosvg to convert Google Quickdraw data set ndjson format to svg images
Home-page: https://github.com/thompson318/ndjsonTosvg
Author: Stephen Thompson
Author-email: YOUR-EMAIL@ucl.ac.uk
License: BSD-3 license
Keywords: medical imaging
Platform: UNKNOWN
Classifier: Development Status :: 3 - Alpha
Classifier: Intended Audience :: Developers
Classifier: Intended Audience :: Healthcare Industry
Classifier: Intended Audience :: Information Technology
Classifier: Intended Audience :: Science/Research
Classifier: License :: OSI Approved :: BSD License
Classifier: Programming Language :: Python
Classifier: Programming Language :: Python :: 2
Classifier: Programming Language :: Python :: 3
Classifier: Topic :: Scientific/Engineering :: Information Analysis
Classifier: Topic :: Scientific/Engineering :: Medical Science Apps.
